interactions/ext/molter/__init__.py
interactions/ext/molter/base.py
interactions/ext/molter/checks.py
interactions/ext/molter/command.py
interactions/ext/molter/context.py
interactions/ext/molter/converters.py
interactions/ext/molter/errors.py
interactions/ext/molter/extension.py
interactions/ext/molter/manager.py
interactions/ext/molter/utils.py
interactions_molter-1.1.0.dist-info/LICENSE
interactions_molter-1.1.0.dist-info/METADATA
interactions_molter-1.1.0.dist-info/WHEEL
interactions_molter-1.1.0.dist-info/top_level.txt
interactions_molter-1.1.0.dist-info/RECORD
