Metadata-Version: 2.1
Name: interactions-molter
Version: 1.1.0
Summary: An extension library for interactions.py to add prefixed commands. A demonstration of molter-core.
Home-page: https://github.com/interactions-py/molter
Author: Astrea49
License: MIT
Project-URL: Documentation, https://interactions-py.github.io/molter/main/
Classifier: Development Status :: 4 - Beta
Classifier: Intended Audience :: Developers
Classifier: Programming Language :: Python :: 3
Classifier: License :: OSI Approved :: MIT License
Classifier: Operating System :: OS Independent
Classifier: Typing :: Typed
Requires-Python: >=3.8.6
License-File: LICENSE
Requires-Dist: discord-py-interactions (>=4.3.0)
Requires-Dist: typing-extensions (>=4.1)
Provides-Extra: docs
Requires-Dist: wheel ; extra == 'docs'
Requires-Dist: furo ; extra == 'docs'
Requires-Dist: Sphinx ; extra == 'docs'
Requires-Dist: sphinx-copybutton ; extra == 'docs'
Requires-Dist: sphinx-hoverxref ; extra == 'docs'
Requires-Dist: enum-tools[sphinx] ; extra == 'docs'
Requires-Dist: sphinxext-opengraph ; extra == 'docs'
Requires-Dist: myst-parser ; extra == 'docs'
